client/__init__.py
client/main.py
client/start.py
client/ws_client.py
client/ws_server.py
client/assets/1.png
client/assets/10.jpg
client/assets/2.jpg
client/assets/3.jpg
client/assets/4.png
client/assets/7.jpg
client/assets/8.jpg
client/assets/9.jpg
client/assets/__init__.py
client/assets/antidote.png
client/assets/armor1.png
client/assets/basicenemy1.png
client/assets/basicenemy2.png
client/assets/chest.png
client/assets/cleric.png
client/assets/crown.png
client/assets/crown1.png
client/assets/crown2.png
client/assets/drink1.png
client/assets/drink2.png
client/assets/enemy.png
client/assets/enemy3.png
client/assets/enemy4.png
client/assets/enemy5.png
client/assets/enemy5_fly.png
client/assets/enemyf.png
client/assets/food1.png
client/assets/food2.png
client/assets/food3.png
client/assets/goblin.png
client/assets/hammer.png
client/assets/mage.png
client/assets/mechape.png
client/assets/merchant.png
client/assets/openchest.png
client/assets/poison.png
client/assets/potion1.png
client/assets/potion2.png
client/assets/range.png
client/assets/room1.jpg
client/assets/room10.jpg
client/assets/room2.jpg
client/assets/room3.jpg
client/assets/room4.jpg
client/assets/room5.jpg
client/assets/room6.jpg
client/assets/room7.jpg
client/assets/room8.jpg
client/assets/room9.jpg
client/assets/speedboots.png
client/assets/sword1.png
client/assets/sword2.png
client/assets/tank.png
client/assets/torch.png
client/assets/warrior.png
client/render_methods/__init__.py
client/render_methods/enemy.py
client/render_methods/move.py
client/render_methods/voting.py
crown_of_the_abyss_client-2.0.1.dist-info/METADATA
crown_of_the_abyss_client-2.0.1.dist-info/WHEEL
crown_of_the_abyss_client-2.0.1.dist-info/entry_points.txt
crown_of_the_abyss_client-2.0.1.dist-info/top_level.txt
crown_of_the_abyss_client-2.0.1.dist-info/RECORD
