Metadata-Version: 2.1
Name: crown-of-the-abyss-client
Version: 2.0.1
Summary: UNKNOWN
Home-page: UNKNOWN
License: UNKNOWN
Platform: UNKNOWN
Requires-Dist: pygame
Requires-Dist: websockets
